cl_logger/__init__.py
cl_logger/http_utils.py
cl_logger/logger.py
cl_logger/sqs_utils.py
cl_logger/trace_context.py
goldcast_cl_logger-0.6.2.dist-info/LICENSE
goldcast_cl_logger-0.6.2.dist-info/METADATA
goldcast_cl_logger-0.6.2.dist-info/WHEEL
goldcast_cl_logger-0.6.2.dist-info/RECORD
