Metadata-Version: 2.3
Name: goldcast-cl-logger
Version: 0.6.2
Summary: A lightweight logging library for Content Lab projects with distributed tracing support
License: MIT
Author: Content Lab Team
Author-email: content-lab@goldcast.io
Requires-Python: >=3.10,<4.0
Classifier: Development Status :: 4 - Beta
Classifier: Intended Audience :: Developers
Classifier: License :: OSI Approved :: MIT License
Classifier: Programming Language :: Python :: 3
Classifier: Programming Language :: Python :: 3.10
Classifier: Programming Language :: Python :: 3.11
Classifier: Programming Language :: Python :: 3.12
Classifier: Programming Language :: Python :: 3.13
Classifier: Topic :: Software Development :: Libraries :: Python Modules
Classifier: Topic :: System :: Logging
Provides-Extra: http
Requires-Dist: requests (>=2.31.0,<3.0.0) ; extra == "http"
Project-URL: Bug Tracker, https://github.com/goldcast/content-lab-backend/issues
Project-URL: Documentation, https://github.com/goldcast/content-lab-backend/tree/main/libraries/cl-logger
Project-URL: Repository, https://github.com/goldcast/content-lab-backend
Project-URL: Source Code, https://github.com/goldcast/content-lab-backend/tree/main/libraries/cl-logger
